LICENSE
README.md
lyytktextbox.py
setup.py
lyytktextbox.egg-info/PKG-INFO
lyytktextbox.egg-info/SOURCES.txt
lyytktextbox.egg-info/dependency_links.txt
lyytktextbox.egg-info/requires.txt
lyytktextbox.egg-info/top_level.txt