Metadata-Version: 2.1
Name: lyytktextbox
Version: 1.1
Summary: yyjdgui for lyy
Author: lyy
Author-email: 
License: MIT
License-File: LICENSE
